{
  "generation": 7,
  "best_f1_score": 0.5912466652246016,
  "best_parameters": {
    "proximity_threshold": 0.5317049841143289,
    "confidence_threshold": 0.5142991393441985,
    "lookback_period": 46,
    "window_size": 3
  },
  "all_time_best_f1": 0.6446673974758973,
  "all_time_best_parameters": {
    "proximity_threshold": 0.6765990378016592,
    "confidence_threshold": 0.3151311589677633,
    "lookback_period": 26,
    "window_size": 3
  },
  "total_backtests": 200,
  "convergence_counter": 3,
  "evolution_runtime_hours": 0.04867250555555556,
  "trials": [
    {
      "params": {
        "proximity_threshold": 0.5595354645792987,
        "confidence_threshold": 0.18168800147082317,
        "lookback_period": 5,
        "window_size": 15
      },
      "value": 0.2292500780872874
    },
    {
      "params": {
        "proximity_threshold": 0.8095195312222785,
        "confidence_threshold": 0.985397457003437,
        "lookback_period": 22,
        "window_size": 13
      },
      "value": 0.23485724114207085
    },
    {
      "params": {
        "proximity_threshold": 0.8173160093968056,
        "confidence_threshold": 0.3802527245653952,
        "lookback_period": 8,
        "window_size": 10
      },
      "value": 0.26218076501355914
    },
    {
      "params": {
        "proximity_threshold": 0.23076518495558,
        "confidence_threshold": 0.012186979317326803,
        "lookback_period": 9,
        "window_size": 12
      },
      "value": 0.20901709401709404
    },
    {
      "params": {
        "proximity_threshold": 0.5317049841143289,
        "confidence_threshold": 0.5142991393441985,
        "lookback_period": 46,
        "window_size": 3
      },
      "value": 0.5912466652246016
    }
  ],
  "timestamp": "2025-10-03T18:51:23.942493"
}